smartroute/__init__.py
smartroute/core/__init__.py
smartroute/core/base.py
smartroute/core/decorators.py
smartroute/core/router.py
smartroute/plugins/__init__.py
smartroute/plugins/logging.py
smartroute/plugins/pydantic.py
smartroute-0.3.0.dist-info/licenses/LICENSE
smartroute-0.3.0.dist-info/METADATA
smartroute-0.3.0.dist-info/WHEEL
smartroute-0.3.0.dist-info/top_level.txt
smartroute-0.3.0.dist-info/RECORD
