Metadata-Version: 2.4
Name: smartroute
Version: 0.3.0
Summary: Instance-scoped routing engine for Python with hierarchical handlers and composable plugins
Author-email: Genropy Team <softwell@softwell.it>
License: MIT
Project-URL: Homepage, https://github.com/genropy/smartroute
Project-URL: Documentation, https://smartroute.readthedocs.io
Project-URL: Repository, https://github.com/genropy/smartroute
Project-URL: Bug Tracker, https://github.com/genropy/smartroute/issues
Keywords: routing,dispatch,plugin-system,instance-bound,hierarchical
Classifier: Development Status :: 3 - Alpha
Classifier: Intended Audience :: Developers
Classifier: License :: OSI Approved :: MIT License
Classifier: Programming Language :: Python :: 3
Classifier: Programming Language :: Python :: 3.10
Classifier: Programming Language :: Python :: 3.11
Classifier: Programming Language :: Python :: 3.12
Classifier: Topic :: Software Development :: Libraries :: Python Modules
Classifier: Topic :: Software Development :: Code Generators
Classifier: Typing :: Typed
Requires-Python: >=3.10
License-File: LICENSE
Requires-Dist: smartseeds>=0.2.0
Provides-Extra: dev
Requires-Dist: pytest>=7.0.0; extra == "dev"
Requires-Dist: pytest-cov>=4.0.0; extra == "dev"
Requires-Dist: black>=23.0.0; extra == "dev"
Requires-Dist: ruff>=0.1.0; extra == "dev"
Requires-Dist: mypy>=1.0.0; extra == "dev"
Provides-Extra: docs
Requires-Dist: sphinx>=8.0.0; extra == "docs"
Requires-Dist: sphinx-rtd-theme>=3.0.0; extra == "docs"
Requires-Dist: sphinx-autodoc-typehints>=3.0.0; extra == "docs"
Requires-Dist: myst-parser>=4.0.0; extra == "docs"
Requires-Dist: sphinxcontrib-mermaid>=1.0.0; extra == "docs"
Provides-Extra: pydantic
Requires-Dist: pydantic>=2.0.0; extra == "pydantic"
Provides-Extra: all
Requires-Dist: pytest>=7.0.0; extra == "all"
Requires-Dist: pytest-cov>=4.0.0; extra == "all"
Requires-Dist: black>=23.0.0; extra == "all"
Requires-Dist: ruff>=0.1.0; extra == "all"
Requires-Dist: mypy>=1.0.0; extra == "all"
Requires-Dist: sphinx>=8.0.0; extra == "all"
Requires-Dist: sphinx-rtd-theme>=3.0.0; extra == "all"
Requires-Dist: sphinx-autodoc-typehints>=3.0.0; extra == "all"
Requires-Dist: myst-parser>=4.0.0; extra == "all"
Requires-Dist: sphinxcontrib-mermaid>=1.0.0; extra == "all"
Requires-Dist: pydantic>=2.0.0; extra == "all"
Dynamic: license-file
